Metadata-Version: 2.1
Name: whaTFRecordsWriter
Version: 0.0.3
Summary: UNKNOWN
Home-page: https://github.com/haideraltahan/whaTFRecordsWriter
Author: Haider Al-Tahan
Author-email: haideraltahan@gmail.com
License: License :: OSI Approved :: MIT License
Platform: UNKNOWN
Classifier: Programming Language :: Python
Requires-Python: >=3.6
